<?xml version="1.0" encoding="utf-8" ?><dwsync><file name="audio.png" server="Macintosh HD/Users/Alex M/Sites/ibs/" local="3347562164" remote="11937496756" /><file name="video.png" server="Macintosh HD/Users/Alex M/Sites/ibs/" local="3347562174" remote="11937496766" /><file name="photos.png" server="Macintosh HD/Users/Alex M/Sites/ibs/" local="3347562181" remote="11937496773" /><file name="audio.png" server="Alex_MiniHD/Work/webfiles/ibs/" local="3347562164" remote="11937496756" /><file name="video.png" server="Alex_MiniHD/Work/webfiles/ibs/" local="3347562174" remote="11937496766" /><file name="photos.png" server="Alex_MiniHD/Work/webfiles/ibs/" local="3347562181" remote="11937496773" /><file name="audio.png" server="ftp.ibs-la.org/test/" local="3347562164" remote="11958831872" /><file name="video.png" server="ftp.ibs-la.org/test/" local="3347562174" remote="11958831872" /><file name="photos.png" server="ftp.ibs-la.org/test/" local="3347562181" remote="11958831872" /><file name="audio.png" server="Macintosh HD/Users/Alex/Sites/ibs/" local="3347562164" remote="11937496756" /><file name="photos.png" server="Macintosh HD/Users/Alex/Sites/ibs/" local="3347562181" remote="11937496773" /><file name="video.png" server="Macintosh HD/Users/Alex/Sites/ibs/" local="3347562174" remote="11937496766" /></dwsync>